google/cloud/alloydb/__init__.py
google/cloud/alloydb/gapic_version.py
google/cloud/alloydb/py.typed
google/cloud/alloydb_v1/__init__.py
google/cloud/alloydb_v1/gapic_metadata.json
google/cloud/alloydb_v1/gapic_version.py
google/cloud/alloydb_v1/py.typed
google/cloud/alloydb_v1/services/__init__.py
google/cloud/alloydb_v1/services/alloy_db_admin/__init__.py
google/cloud/alloydb_v1/services/alloy_db_admin/async_client.py
google/cloud/alloydb_v1/services/alloy_db_admin/client.py
google/cloud/alloydb_v1/services/alloy_db_admin/pagers.py
google/cloud/alloydb_v1/services/alloy_db_admin/transports/__init__.py
google/cloud/alloydb_v1/services/alloy_db_admin/transports/base.py
google/cloud/alloydb_v1/services/alloy_db_admin/transports/grpc.py
google/cloud/alloydb_v1/services/alloy_db_admin/transports/grpc_asyncio.py
google/cloud/alloydb_v1/services/alloy_db_admin/transports/rest.py
google/cloud/alloydb_v1/services/alloy_db_admin/transports/rest_base.py
google/cloud/alloydb_v1/services/alloy_dbcsql_admin/__init__.py
google/cloud/alloydb_v1/services/alloy_dbcsql_admin/async_client.py
google/cloud/alloydb_v1/services/alloy_dbcsql_admin/client.py
google/cloud/alloydb_v1/services/alloy_dbcsql_admin/transports/__init__.py
google/cloud/alloydb_v1/services/alloy_dbcsql_admin/transports/base.py
google/cloud/alloydb_v1/services/alloy_dbcsql_admin/transports/grpc.py
google/cloud/alloydb_v1/services/alloy_dbcsql_admin/transports/grpc_asyncio.py
google/cloud/alloydb_v1/services/alloy_dbcsql_admin/transports/rest.py
google/cloud/alloydb_v1/services/alloy_dbcsql_admin/transports/rest_base.py
google/cloud/alloydb_v1/types/__init__.py
google/cloud/alloydb_v1/types/csql_resources.py
google/cloud/alloydb_v1/types/csql_service.py
google/cloud/alloydb_v1/types/data_model.py
google/cloud/alloydb_v1/types/resources.py
google/cloud/alloydb_v1/types/service.py
google/cloud/alloydb_v1alpha/__init__.py
google/cloud/alloydb_v1alpha/gapic_metadata.json
google/cloud/alloydb_v1alpha/gapic_version.py
google_cloud_alloydb-0.4.6.dist-info/LICENSE
google_cloud_alloydb-0.4.6.dist-info/METADATA
google_cloud_alloydb-0.4.6.dist-info/WHEEL
google_cloud_alloydb-0.4.6.dist-info/top_level.txt
google_cloud_alloydb-0.4.6.dist-info/RECORD
